phoenix_sdk/__init__.py
phoenix_sdk/api_client.py
phoenix_sdk/api_response.py
phoenix_sdk/configuration.py
phoenix_sdk/exceptions.py
phoenix_sdk/py.typed
phoenix_sdk/rest.py
phoenix_sdk/api/__init__.py
phoenix_sdk/api/address_api.py
phoenix_sdk/api/company_api.py
phoenix_sdk/api/device_api.py
phoenix_sdk/api/gateways_api.py
phoenix_sdk/api/orders_api.py
phoenix_sdk/api/pandadoc_api.py
phoenix_sdk/api/stats_api.py
phoenix_sdk/api/stripe_api.py
phoenix_sdk/api/unit_api.py
phoenix_sdk/models/__init__.py
phoenix_sdk/models/address_schema_in.py
phoenix_sdk/models/address_schema_out.py
phoenix_sdk/models/company_members_patch_schema_in.py
phoenix_sdk/models/company_patch_schema_in.py
phoenix_sdk/models/company_schema_in.py
phoenix_sdk/models/company_schema_out.py
phoenix_sdk/models/country_enum.py
phoenix_sdk/models/data.py
phoenix_sdk/models/device_config_min.py
phoenix_sdk/models/device_config_schema_in.py
phoenix_sdk/models/device_config_schema_out.py
phoenix_sdk/models/device_schema_in.py
phoenix_sdk/models/device_schema_out.py
phoenix_sdk/models/device_types_schema_in.py
phoenix_sdk/models/device_types_schema_out.py
phoenix_sdk/models/event_type.py
phoenix_sdk/models/gateway_schema_in.py
phoenix_sdk/models/gateway_schema_out.py
phoenix_sdk/models/http_validation_error.py
phoenix_sdk/models/order_claim_invoice_schema_in.py
phoenix_sdk/models/order_claim_items_schema_in.py
phoenix_sdk/models/order_claim_items_schema_out.py
phoenix_sdk/models/order_claim_status.py
phoenix_sdk/models/order_status.py
phoenix_sdk/models/page_address_schema_out.py
phoenix_sdk/models/page_company_schema_out.py
phoenix_sdk/models/page_device_config_schema_out.py
phoenix_sdk/models/page_device_schema_out.py
phoenix_sdk/models/page_unit_event_schema_out.py
phoenix_sdk/models/page_unit_group_schema_out.py
phoenix_sdk/models/page_unit_schema_out.py
phoenix_sdk/models/shop_order_items_schema_in.py
phoenix_sdk/models/shop_order_patch_schema_in.py
phoenix_sdk/models/shop_order_schema_in.py
noahenergy_phoenix_sdk-3.2.1.dist-info/METADATA
noahenergy_phoenix_sdk-3.2.1.dist-info/WHEEL
noahenergy_phoenix_sdk-3.2.1.dist-info/top_level.txt
noahenergy_phoenix_sdk-3.2.1.dist-info/RECORD
