Metadata-Version: 2.4
Name: noahENERGY-phoenix_sdk
Version: 3.2.1
Summary: Phoenix API
Home-page: https://gitlab.com/smart-building-solutions/phoenix
Author: OpenAPI Generator community
Author-email: team@openapitools.org
Keywords: OpenAPI,OpenAPI-Generator,Phoenix API
Requires-Dist: urllib3<3.0.0,>=1.25.3
Requires-Dist: python-dateutil>=2.8.2
Requires-Dist: pydantic>=2
Requires-Dist: typing-extensions>=4.7.1
Dynamic: author
Dynamic: author-email
Dynamic: description
Dynamic: description-content-type
Dynamic: home-page
Dynamic: keywords
Dynamic: requires-dist
Dynamic: summary
